LICENSE
MANIFEST.in
README.rst
setup.py
CrawlerCodePythonTools.egg-info/PKG-INFO
CrawlerCodePythonTools.egg-info/SOURCES.txt
CrawlerCodePythonTools.egg-info/dependency_links.txt
CrawlerCodePythonTools.egg-info/requires.txt
CrawlerCodePythonTools.egg-info/top_level.txt
pythontools/core/__init__.py
pythontools/core/config.py
pythontools/core/cronjob.py
pythontools/core/events.py
pythontools/core/logger.py
pythontools/core/tools.py
pythontools/dev/__init__.py
pythontools/dev/crypthography.py
pythontools/dev/dev.py
pythontools/identity/__init__.py
pythontools/identity/identity.py
pythontools/sockets/__init__.py
pythontools/sockets/client.py
pythontools/sockets/relay.py
pythontools/sockets/server.py
pythontools/telegram/__init__.py
pythontools/telegram/api.py