Metadata-Version: 2.1
Name: CrawlerCodePythonTools
Version: 1.5.4
Summary: Tools for Python
Home-page: https://github.com/CrawlerCode
Author: CrawlerCode
Author-email: 
License: MIT
Platform: UNKNOWN
License-File: LICENSE
